s2b_task/__init__.py
s2b_task/action.py
s2b_task/exc.py
s2b_task/schema.py
s2b_task/storage.py
s2b_task/task_executor.py
s2b_task-0.0.5.dist-info/entry_points.txt
s2b_task-0.0.5.dist-info/LICENSE
s2b_task-0.0.5.dist-info/WHEEL
s2b_task-0.0.5.dist-info/METADATA
s2b_task-0.0.5.dist-info/RECORD
